tmcli/__init__.py
tmcli/__main__.py
tmcli/benchmark/__init__.py
tmcli/benchmark/bench.py
tmcli/benchmark/model_configs.json
tm_cli-0.1.0.dist-info/METADATA
tm_cli-0.1.0.dist-info/WHEEL
tm_cli-0.1.0.dist-info/entry_points.txt
tm_cli-0.1.0.dist-info/top_level.txt
tm_cli-0.1.0.dist-info/RECORD
