Metadata-Version: 2.4
Name: tm-cli
Version: 0.1.0
Summary: TensorMesh CLI tool suite
Classifier: Programming Language :: Python :: 3
Classifier: Operating System :: OS Independent
Requires-Python: >=3.9
